<?xml version="1.0" ?>
<Rsync>
	<Host_Info>
		<Host>192.168.9.68</Host>
		<Path>/home/</Path>
		<Time>2008-12-19 01:18:52</Time>
		<Sync_ID>16</Sync_ID>
	</Host_Info>
	<Sync_List>
	<Sync_Info>
		<Path>/home/devicevm/apt_repository/pool/test1/released</Path>
		<FileName>Kernel.Splashtop.Proto_0.3.6.0.bix</FileName>
	</Sync_Info>
	<Sync_Info>
		<Path>/home/devicevm/exe</Path>
		<FileName>HA-vnc-4.0-x86_win32-KC_1225964814.exe</FileName>
	</Sync_Info>
	<Sync_Info>
		<Path>/home/devicevm/exe</Path>
		<FileName>WinSCP4_1225964814.exe</FileName>
	</Sync_Info>
	</Sync_List>
</Rsync>
